wavelength_test/__init__.py
wavelength_test/integration/__init__.py
wavelength_test/integration/cognito/__init__.py
wavelength_test/integration/cognito/cognito_client.py
wavelength_test/integration/util/__init__.py
wavelength_test/integration/util/aws_utils.py
wavelength_test/integration/util/event_to_request.py
wavelength_test/integration/util/invoker_base.py
wavelength_test/integration/util/lambda_invoker_aws.py
wavelength_test/integration/util/lambda_invoker_local.py
wavelength_test/integration/util/lambda_util.py
wavelength_test/integration/util/mock_constants.py
wavelength_test-0.0.3.dist-info/METADATA
wavelength_test-0.0.3.dist-info/WHEEL
wavelength_test-0.0.3.dist-info/top_level.txt
wavelength_test-0.0.3.dist-info/RECORD
