Metadata-Version: 2.1
Name: wavelength-test
Version: 0.0.3
Summary: Common Utilities for Serverless Testing
Home-page: UNKNOWN
Author: Wavelength Serverless Team
Author-email: dev@teamwavelength.com
License: UNKNOWN
Keywords: Lambda,Serverless,AWS,Integration Testing,Testing,Local Development
Platform: UNKNOWN
Classifier: Programming Language :: Python :: 3
